paddyhong/__init__.py
paddyhong/main.py
paddyhong/new-def.py
paddyhong/new-py.py
paddyhong/setup.py
paddyhong-0.1.0.dist-info/METADATA
paddyhong-0.1.0.dist-info/WHEEL
paddyhong-0.1.0.dist-info/top_level.txt
paddyhong-0.1.0.dist-info/RECORD
